setup.py
BiblioPixelTriggers/__init__.py
BiblioPixelTriggers/bt_proximity.py
BiblioPixelTriggers/crontab.py
BiblioPixelTriggers.egg-info/PKG-INFO
BiblioPixelTriggers.egg-info/SOURCES.txt
BiblioPixelTriggers.egg-info/dependency_links.txt
BiblioPixelTriggers.egg-info/requires.txt
BiblioPixelTriggers.egg-info/top_level.txt
BiblioPixelTriggers/solar/__init__.py
BiblioPixelTriggers/solar/sunrise_sunset.py