Metadata-Version: 1.1
Name: BiblioPixelTriggers
Version: 1.0.2
Summary: BiblioPixel Remote UI Animation Triggers
Home-page: https://github.com/ManiacalLabs/BiblioPixelNeoSegment
Author: Adam Haile
Author-email: adam@maniacallabs.com
License: MIT
Platform: UNKNOWN
Classifier: Development Status :: 5 - Production/Stable
Classifier: License :: OSI Approved :: MIT License
Classifier: Programming Language :: Python :: 3.4
Classifier: Programming Language :: Python :: 3.5
Classifier: Programming Language :: Python :: 3.6
